Metadata-Version: 2.1
Name: odoo12-addon-stock-production-lot-multi-company
Version: 12.0.1.0.0.99.dev8
Summary: Make serial numbers multi-company aware
Home-page: https://github.com/OCA/multi-company
Author: OdooMRP team, AvanzOSC, Serv. Tecnol. Avanzados - Pedro M. Baeza, Odoo Community Association (OCA)
Author-email: support@odoo-community.org
License: AGPL-3
Platform: UNKNOWN
Classifier: Programming Language :: Python
Classifier: Framework :: Odoo
Classifier: Framework :: Odoo :: 12.0
Classifier: License :: OSI Approved :: GNU Affero General Public License v3
Requires-Python: >=3.5
Requires-Dist: odoo <12.1dev,>=12.0a
